clonesearch/__init__.py
clonesearch/data_file.py
clonesearch/main.py
clonesearch/utils.py
clone_search_abs-0.21.dist-info/LICENSE
clone_search_abs-0.21.dist-info/METADATA
clone_search_abs-0.21.dist-info/WHEEL
clone_search_abs-0.21.dist-info/top_level.txt
clone_search_abs-0.21.dist-info/RECORD
