Metadata-Version: 2.1
Name: clone-search-abs
Version: 0.21
License-File: LICENSE
Requires-Dist: pandas (>=1.3.0)
Requires-Dist: levenshtein (>=0.23.0)
